main.py
reccoon-0.0.1.dist-info/METADATA
reccoon-0.0.1.dist-info/WHEEL
reccoon-0.0.1.dist-info/top_level.txt
reccoon-0.0.1.dist-info/RECORD
