Metadata-Version: 2.1
Name: reccoon
Version: 0.0.1
Summary: kyobo
Home-page: https://github.com/Jinmun-Park/reccoon
Author: Jinmun Park
Author-email: pjm9827@gmail.com
